examples/example_1/example_1.py
examples/example_2/example_2.py
examples/example_3/example_3.py
examples/example_4/example_4.py
shapelets/__init__.py
shapelets/entrypoints.py
shapelets/functions.py
shapelets/run.py
shapelets/astronomy/__init__.py
shapelets/astronomy/galaxy.py
shapelets/astronomy/misc.py
shapelets/self_assembly/__init__.py
shapelets/self_assembly/_rdistance.cpp
shapelets/self_assembly/_rdistance_mac_arm64.so
shapelets/self_assembly/_rdistance_nix_amd64.so
shapelets/self_assembly/_rdistance_win_amd64.so
shapelets/self_assembly/apps.py
shapelets/self_assembly/auto.py
shapelets/self_assembly/misc.py
shapelets/self_assembly/tools.py
shapelets/tests/__init__.py
shapelets/tests/test_astronomy_basic.py
shapelets/tests/test_self_assembly_apps.py
shapelets/tests/test_self_assembly_tools.py
shapelets/tests/test_shapelet_functions.py
shapelets/tests/images/galaxies.fits
shapelets/tests/images/hexSIM1.png
shapelets/tests/images/lamSIM1.png
shapelets-1.3.dist-info/licenses/AUTHORS.md
shapelets-1.3.dist-info/licenses/LICENSE
shapelets-1.3.dist-info/METADATA
shapelets-1.3.dist-info/WHEEL
shapelets-1.3.dist-info/entry_points.txt
shapelets-1.3.dist-info/top_level.txt
shapelets-1.3.dist-info/RECORD
