Metadata-Version: 2.4
Name: shapelets
Version: 1.3
Summary: Shapelets provide reference access to various shapelet functions and some of their applications.
Author: Matthew Peres Tino, Abbas Yusuf Abdulaziz, Cameron Chin, Nasser Mohieddin Abukhdeir, Robert Suderman, Thomas Akdeniz
Author-email: Matthew Peres Tino <mptino@uwaterloo.ca>
License:                   GNU LESSER GENERAL PUBLIC LICENSE
Project-URL: homepage, https://uw-comphys.github.io/shapelets
Project-URL: documentation, https://uw-comphys.github.io/shapelets
Project-URL: source, https://github.com/uw-comphys/shapelets
Project-URL: download, https://github.com/uw-comphys/shapelets/releases
Project-URL: tracker, https://github.com/uw-comphys/shapelets/issues
Keywords: shapelets,image analysis
Classifier: Topic :: Scientific/Engineering :: Physics
Classifier: License :: OSI Approved :: GNU Lesser General Public License v2 or later (LGPLv2+)
Classifier: Programming Language :: Python :: 3 :: Only
Classifier: Operating System :: Microsoft :: Windows
Classifier: Operating System :: POSIX :: Linux
Classifier: Operating System :: POSIX
Classifier: Operating System :: Unix
Classifier: Operating System :: MacOS
Requires-Python: >=3.10
License-File: LICENSE
License-File: AUTHORS.md
Requires-Dist: astropy
Requires-Dist: matplotlib
Requires-Dist: numpy<2.0
Requires-Dist: opencv-python
Requires-Dist: scikit-learn
Requires-Dist: scikit-image
Requires-Dist: sep
Requires-Dist: scipy
Requires-Dist: tensorflow
Dynamic: license-file
